aymara_ai/__init__.py
aymara_ai/_base_client.py
aymara_ai/_client.py
aymara_ai/_compat.py
aymara_ai/_constants.py
aymara_ai/_exceptions.py
aymara_ai/_files.py
aymara_ai/_models.py
aymara_ai/_qs.py
aymara_ai/_resource.py
aymara_ai/_response.py
aymara_ai/_streaming.py
aymara_ai/_types.py
aymara_ai/_version.py
aymara_ai/pagination.py
aymara_ai/py.typed
aymara_ai/_utils/__init__.py
aymara_ai/_utils/_compat.py
aymara_ai/_utils/_datetime_parse.py
aymara_ai/_utils/_logs.py
aymara_ai/_utils/_proxy.py
aymara_ai/_utils/_reflection.py
aymara_ai/_utils/_resources_proxy.py
aymara_ai/_utils/_streams.py
aymara_ai/_utils/_sync.py
aymara_ai/_utils/_transform.py
aymara_ai/_utils/_typing.py
aymara_ai/_utils/_utils.py
aymara_ai/lib/.keep
aymara_ai/lib/__init__.py
aymara_ai/lib/async_utils.py
aymara_ai/lib/df.py
aymara_ai/lib/examples_utils.py
aymara_ai/lib/images_utils.py
aymara_ai/lib/logger.py
aymara_ai/lib/plot.py
aymara_ai/lib/runner.py
aymara_ai/lib/status.py
aymara_ai/lib/uploads.py
aymara_ai/resources/__init__.py
aymara_ai/resources/eval_types.py
aymara_ai/resources/files.py
aymara_ai/resources/health.py
aymara_ai/resources/reports.py
aymara_ai/resources/evals/__init__.py
aymara_ai/resources/evals/evals.py
aymara_ai/resources/evals/runs.py
aymara_ai/types/__init__.py
aymara_ai/types/ai_instruction.py
aymara_ai/types/eval.py
aymara_ai/types/eval_analyze_params.py
aymara_ai/types/eval_analyze_response.py
aymara_ai/types/eval_create_params.py
aymara_ai/types/eval_delete_params.py
aymara_ai/types/eval_get_params.py
aymara_ai/types/eval_list_params.py
aymara_ai/types/eval_list_prompts_params.py
aymara_ai/types/eval_prompt.py
aymara_ai/types/eval_response_param.py
aymara_ai/types/eval_suite_report.py
aymara_ai/types/eval_type.py
aymara_ai/types/eval_type_find_instructions_params.py
aymara_ai/types/eval_type_list_instructions_params.py
aymara_ai/types/eval_type_list_params.py
aymara_ai/types/eval_update_params.py
aymara_ai/types/file_create_params.py
aymara_ai_sdk-1.2.0.dist-info/METADATA
aymara_ai_sdk-1.2.0.dist-info/WHEEL
aymara_ai_sdk-1.2.0.dist-info/licenses/LICENSE
aymara_ai_sdk-1.2.0.dist-info/RECORD
