Metadata-Version: 2.3
Name: aymara-ai-sdk
Version: 1.2.0
Summary: The official Python library for the aymara-ai API
Project-URL: Homepage, https://github.com/aymara-ai/aymara-sdk-python
Project-URL: Repository, https://github.com/aymara-ai/aymara-sdk-python
Author-email: Aymara AI <support@aymara.ai>
License: Apache-2.0
Classifier: Intended Audience :: Developers
Classifier: License :: OSI Approved :: Apache Software License
Classifier: Operating System :: MacOS
Classifier: Operating System :: Microsoft :: Windows
Classifier: Operating System :: OS Independent
Classifier: Operating System :: POSIX
Classifier: Operating System :: POSIX :: Linux
Classifier: Programming Language :: Python :: 3.9
Classifier: Programming Language :: Python :: 3.10
Classifier: Programming Language :: Python :: 3.11
Classifier: Programming Language :: Python :: 3.12
Classifier: Programming Language :: Python :: 3.13
Classifier: Programming Language :: Python :: 3.14
Classifier: Topic :: Software Development :: Libraries :: Python Modules
Classifier: Typing :: Typed
Requires-Python: >=3.9
Requires-Dist: aiofiles>=24.1.0
Requires-Dist: anyio<5,>=3.5.0
Requires-Dist: boto3>=1.37.37
Requires-Dist: colorama>=0.4.6
Requires-Dist: distro<2,>=1.7.0
Requires-Dist: httpx<1,>=0.23.0
Requires-Dist: ipykernel>=6.29.5
Requires-Dist: ipywidgets>=8.1.5
Requires-Dist: jupyter>=1.1.0
Requires-Dist: matplotlib>=3.9.4
Requires-Dist: pandas>=2.2.3
Requires-Dist: pydantic<3,>=1.9.0
Requires-Dist: sniffio
Requires-Dist: tqdm>=4.67.1
Requires-Dist: typing-extensions<5,>=4.10
Provides-Extra: aiohttp
Requires-Dist: aiohttp; extra == 'aiohttp'
Requires-Dist: httpx-aiohttp>=0.1.9; extra == 'aiohttp'
